Metadata-Version: 2.1
Name: oneNeuron-pypi-achievehigh
Version: 0.0.3
Summary: its a implementation of Perceptron
Home-page: https://github.com/achievehigh/oneNeuron_pypi
Author: USER_NAME
Author-email: achievehigh.nevergiveup@gmail.com
License: UNKNOWN
Project-URL: Bug Tracker, https://github.com/achievehigh/oneNeuron_pypi/issues
Platform: UNKNOWN
Classifier: Programming Language :: Python :: 3
Classifier: License :: OSI Approved :: MIT License
Classifier: Operating System :: OS Independent
Requires-Python: >=3.7
License-File: LICENSE
Requires-Dist: numpy
Requires-Dist: tqdm
